{
    "horse_db": {
        "Speedy": {
            "Parent1": "",
            "Parent2": "",
            "Status": "Alive",
            "OriginBlood": "Star Strider",
            "Generation": "",
            "Speed": 12.06,
            "Jump": 4.75,
            "Health": 24.0,
            "Appearance": "Black w/ White Spots"
        },
        "Blondy": {
            "Parent1": "",
            "Parent2": "",
            "Status": "Dead",
            "OriginBlood": "Celestial Grass",
            "Generation": "",
            "Speed": 11.88,
            "Jump": 2.15,
            "Health": 27.0,
            "Appearance": "Chestnut w/ White Patches"
        },
        "Whitty I": {
            "Parent1": "",
            "Parent2": "",
            "Status": "Dead",
            "OriginBlood": "Thunder Blood",
            "Generation": "",
            "Speed": 11.02,
            "Jump": 2.2,
            "Health": 25.0,
            "Appearance": "White w/ White Spots"
        },
        "Spotty": {
            "Parent1": "",
            "Parent2": "",
            "Status": "Dead",
            "OriginBlood": "Thunder Blood",
            "Generation": "",
            "Speed": 11.01,
            "Jump": 3.78,
            "Health": 24.0,
            "Appearance": "Dark Brown w/ White Spots"
        },
        "Camemille": {
            "Parent1": "",
            "Parent2": "",
            "Status": "Dead",
            "OriginBlood": "Frostmane",
            "Generation": "",
            "Speed": 10.85,
            "Jump": 2.58,
            "Health": 22.0,
            "Appearance": "Creamy w/ None"
        },
        "White V": {
            "Parent1": "",
            "Parent2": "",
            "Status": "Dead",
            "OriginBlood": "Frostmane",
            "Generation": "",
            "Speed": 10.53,
            "Jump": 2.53,
            "Health": 21.0,
            "Appearance": "White w/ None"
        },
        "Pure": {
            "Parent1": "",
            "Parent2": "",
            "Status": "Dead",
            "OriginBlood": "Emberhoof",
            "Generation": "",
            "Speed": 10.44,
            "Jump": 1.58,
            "Health": 25.0,
            "Appearance": "Dark Brown w/ None"
        },
        "Scorchback": {
            "Parent1": "",
            "Parent2": "",
            "Status": "Dead",
            "OriginBlood": "Emberhoof",
            "Generation": "",
            "Speed": 10.21,
            "Jump": 3.14,
            "Health": 24.0,
            "Appearance": "Creamy w/ Black Dots"
        },
        "Snail": {
            "Parent1": "",
            "Parent2": "",
            "Status": "Dead",
            "OriginBlood": "Slothsoul",
            "Generation": "",
            "Speed": 5.73,
            "Jump": 3.23,
            "Health": 22.0,
            "Appearance": "Chestnut w/ White Spots"
        },
        "Gray": {
            "Parent1": "",
            "Parent2": "",
            "Status": "Dead",
            "OriginBlood": "Slothsoul",
            "Generation": "",
            "Speed": 7.78,
            "Jump": 3.82,
            "Health": 25.0,
            "Appearance": "Gray w/ White Spots"
        },
        "Whitty II": {
            "Parent1": "Spotty",
            "Parent2": "Whitty I",
            "Status": "Dead",
            "OriginBlood": "MIXED_SPECIAL",
            "Generation": "",
            "Speed": 11.63,
            "Jump": 0.0,
            "Health": 0.0,
            "Appearance": "White w/ White Spots"
        },
        "Cruiser": {
            "Parent1": "Speedy",
            "Parent2": "Blondy",
            "Status": "Alive",
            "OriginBlood": "",
            "Generation": "",
            "Speed": 11.95,
            "Jump": 3.68,
            "Health": 24.7,
            "Appearance": "Dark Brown w/ White Patches"
        },
        "Stripe": {
            "Parent1": "Pure",
            "Parent2": "Scorchback",
            "Status": "Dead",
            "OriginBlood": "",
            "Generation": "",
            "Speed": 11.06,
            "Jump": 0.0,
            "Health": 0.0,
            "Appearance": "Creamy w/ None"
        },
        "Blackback": {
            "Parent1": "Snail",
            "Parent2": "Gray",
            "Status": "Dead",
            "OriginBlood": "",
            "Generation": "",
            "Speed": 5.61,
            "Jump": 0.0,
            "Health": 0.0,
            "Appearance": "Gray w/ Black Spots"
        },
        "White Face": {
            "Parent1": "Camemille",
            "Parent2": "White V",
            "Status": "Dead",
            "OriginBlood": "",
            "Generation": "",
            "Speed": 9.86,
            "Jump": 0.0,
            "Health": 0.0,
            "Appearance": ""
        },
        "Scorchback II": {
            "Parent1": "Blondy",
            "Parent2": "Whitty II",
            "Status": "Dead",
            "OriginBlood": "",
            "Generation": "",
            "Speed": 11.78,
            "Jump": 0.0,
            "Health": 0.0,
            "Appearance": "Creamy w/ Black Dots"
        },
        "Speedy II": {
            "Parent1": "Speedy",
            "Parent2": "Cruiser",
            "Status": "Dead",
            "OriginBlood": "",
            "Generation": "",
            "Speed": 11.28,
            "Jump": 0.0,
            "Health": 0.0,
            "Appearance": "Black w/ White Dots"
        },
        "Camspot": {
            "Parent1": "Stripe",
            "Parent2": "Whitty I",
            "Status": "Dead",
            "OriginBlood": "",
            "Generation": "",
            "Speed": 11.22,
            "Jump": 0.0,
            "Health": 0.0,
            "Appearance": "Creamy w/ White Dots"
        },
        "Spotty II": {
            "Parent1": "Spotty",
            "Parent2": "Camemille",
            "Status": "Dead",
            "OriginBlood": "",
            "Generation": "",
            "Speed": 10.95,
            "Jump": 0.0,
            "Health": 0.0,
            "Appearance": ""
        },
        "Pure Spots": {
            "Parent1": "White V",
            "Parent2": "Pure",
            "Status": "Dead",
            "OriginBlood": "",
            "Generation": "",
            "Speed": 10.28,
            "Jump": 0.0,
            "Health": 0.0,
            "Appearance": ""
        },
        "White VI": {
            "Parent1": "White V",
            "Parent2": "Pure",
            "Status": "Dead",
            "OriginBlood": "",
            "Generation": "",
            "Speed": 10.11,
            "Jump": 0.0,
            "Health": 0.0,
            "Appearance": ""
        },
        "Gray II": {
            "Parent1": "Snail",
            "Parent2": "Blackback",
            "Status": "Dead",
            "OriginBlood": "",
            "Generation": "",
            "Speed": 5.54,
            "Jump": 0.0,
            "Health": 0.0,
            "Appearance": "Gray w/ White Stockings/Blaze"
        },
        "White VII": {
            "Parent1": "Pure",
            "Parent2": "White V",
            "Status": "Dead",
            "OriginBlood": "",
            "Generation": "",
            "Speed": 10.02,
            "Jump": 0.0,
            "Health": 0.0,
            "Appearance": ""
        },
        "Camspot II": {
            "Parent1": "Camemille",
            "Parent2": "Spotty II",
            "Status": "Dead",
            "OriginBlood": "",
            "Generation": "",
            "Speed": 10.28,
            "Jump": 2.88,
            "Health": 22.2,
            "Appearance": "Creamy w/ Rusty Spots"
        },
        "White VIII": {
            "Parent1": "Spotty",
            "Parent2": "Whitty I",
            "Status": "Dead",
            "OriginBlood": "",
            "Generation": "",
            "Speed": 11.34,
            "Jump": 0.0,
            "Health": 0.0,
            "Appearance": "Creamy w/ White Dots"
        },
        "Camemille II": {
            "Parent1": "Stripe",
            "Parent2": "Camspot",
            "Status": "Dead",
            "OriginBlood": "",
            "Generation": "",
            "Speed": 11.32,
            "Jump": 0.0,
            "Health": 0.0,
            "Appearance": ""
        },
        "White IX": {
            "Parent1": "Speedy II",
            "Parent2": "Whitty II",
            "Status": "Dead",
            "OriginBlood": "",
            "Generation": "",
            "Speed": 10.37,
            "Jump": 0.0,
            "Health": 0.0,
            "Appearance": ""
        },
        "Scorchback III": {
            "Parent1": "Scorchback II",
            "Parent2": "Blondy",
            "Status": "Dead",
            "OriginBlood": "",
            "Generation": "",
            "Speed": 11.54,
            "Jump": 0.0,
            "Health": 0.0,
            "Appearance": ""
        },
        "Spooky": {
            "Parent1": "Cruiser",
            "Parent2": "Speedy",
            "Status": "Dead",
            "OriginBlood": "",
            "Generation": "",
            "Speed": 11.93,
            "Jump": 0.0,
            "Health": 0.0,
            "Appearance": "Black w/ White Patches"
        },
        "Blackback II": {
            "Parent1": "Gray II",
            "Parent2": "Blackback",
            "Status": "Dead",
            "OriginBlood": "",
            "Generation": "",
            "Speed": 5.85,
            "Jump": 0.0,
            "Health": 0.0,
            "Appearance": ""
        },
        "Spotty III": {
            "Parent1": "Spotty II",
            "Parent2": "Camemille",
            "Status": "Dead",
            "OriginBlood": "",
            "Generation": "",
            "Speed": 10.77,
            "Jump": 0.0,
            "Health": 0.0,
            "Appearance": ""
        },
        "Camemille III": {
            "Parent1": "Spotty II",
            "Parent2": "Camemille",
            "Status": "Dead",
            "OriginBlood": "",
            "Generation": "",
            "Speed": 10.15,
            "Jump": 0.0,
            "Health": 0.0,
            "Appearance": ""
        },
        "Pure II": {
            "Parent1": "Spotty II",
            "Parent2": "Camemille",
            "Status": "Dead",
            "OriginBlood": "",
            "Generation": "",
            "Speed": 10.61,
            "Jump": 0.0,
            "Health": 0.0,
            "Appearance": ""
        },
        "Blotty": {
            "Parent1": "Whitty I",
            "Parent2": "Spotty",
            "Status": "Dead",
            "OriginBlood": "",
            "Generation": "",
            "Speed": 10.79,
            "Jump": 0.0,
            "Health": 0.0,
            "Appearance": ""
        },
        "Stripe II": {
            "Parent1": "Stripe",
            "Parent2": "Camspot",
            "Status": "Alive",
            "OriginBlood": "",
            "Generation": "",
            "Speed": 11.99,
            "Jump": 2.18,
            "Health": 25.2,
            "Appearance": "Creamy w/ None"
        },
        "Camspot III": {
            "Parent1": "Speedy II",
            "Parent2": "Camemille II",
            "Status": "Dead",
            "OriginBlood": "",
            "Generation": "",
            "Speed": 11.15,
            "Jump": 0.0,
            "Health": 0.0,
            "Appearance": "Creamy w/ White Dots"
        },
        "Mirage": {
            "Parent1": "White VIII",
            "Parent2": "Scorchback III",
            "Status": "Dead",
            "OriginBlood": "",
            "Generation": "",
            "Speed": 11.6,
            "Jump": 0.0,
            "Health": 0.0,
            "Appearance": "White w/ Black Dots"
        },
        "Mirage II": {
            "Parent1": "Whitty II",
            "Parent2": "Scorchback II",
            "Status": "Alive",
            "OriginBlood": "",
            "Generation": "",
            "Speed": 12.17,
            "Jump": 3.23,
            "Health": 28.0,
            "Appearance": "White w/ Black Dots"
        },
        "Blondy II": {
            "Parent1": "Blondy",
            "Parent2": "Spooky",
            "Status": "Dead",
            "OriginBlood": "",
            "Generation": "",
            "Speed": 11.5,
            "Jump": 0.0,
            "Health": 0.0,
            "Appearance": ""
        },
        "Cruiser II": {
            "Parent1": "Cruiser",
            "Parent2": "Speedy",
            "Status": "Alive",
            "OriginBlood": "",
            "Generation": "",
            "Speed": 12.58,
            "Jump": 4.87,
            "Health": 23.8,
            "Appearance": "Black w/ White Dots"
        },
        "Gray III": {
            "Parent1": "Gray II",
            "Parent2": "Blackback",
            "Status": "Alive",
            "OriginBlood": "",
            "Generation": "",
            "Speed": 4.97,
            "Jump": 2.69,
            "Health": 21.7,
            "Appearance": "Gray w/ White Stockings/Blaze"
        },
        "Camemille IV": {
            "Parent1": "Spotty II",
            "Parent2": "Camemille",
            "Status": "Dead",
            "OriginBlood": "",
            "Generation": "",
            "Speed": 10.52,
            "Jump": 3.6,
            "Health": 22.4,
            "Appearance": "Creamy w/ None"
        },
        "Camemille V": {
            "Parent1": "Spotty II",
            "Parent2": "Camemille",
            "Status": "Dead",
            "OriginBlood": "",
            "Generation": "",
            "Speed": 11.37,
            "Jump": 0.0,
            "Health": 0.0,
            "Appearance": ""
        },
        "Camemille VI": {
            "Parent1": "Speedy II",
            "Parent2": "Camemille II",
            "Status": "Dead",
            "OriginBlood": "",
            "Generation": "",
            "Speed": 10.98,
            "Jump": 0.0,
            "Health": 0.0,
            "Appearance": ""
        },
        "Camspot IV": {
            "Parent1": "White VIII",
            "Parent2": "Camemille V",
            "Status": "Dead",
            "OriginBlood": "",
            "Generation": "",
            "Speed": 11.94,
            "Jump": 0.0,
            "Health": 0.0,
            "Appearance": "Creamy w/ White Dots"
        },
        "Blondy III": {
            "Parent1": "Blondy II",
            "Parent2": "Scorchback III",
            "Status": "Dead",
            "OriginBlood": "",
            "Generation": "",
            "Speed": 11.52,
            "Jump": 0.0,
            "Health": 0.0,
            "Appearance": ""
        },
        "Mirage III": {
            "Parent1": "Mirage",
            "Parent2": "Whitty II",
            "Status": "Dead",
            "OriginBlood": "",
            "Generation": "",
            "Speed": 11.36,
            "Jump": 0.0,
            "Health": 0.0,
            "Appearance": ""
        },
        "White Socks I": {
            "Parent1": "Scorchback II",
            "Parent2": "Blondy",
            "Status": "Alive",
            "OriginBlood": "",
            "Generation": "",
            "Speed": 12.33,
            "Jump": 1.67,
            "Health": 27.0,
            "Appearance": "Chestnut w/ White Stockings/Blaze"
        },
        "Cruiser III": {
            "Parent1": "Spooky",
            "Parent2": "Cruiser",
            "Status": "Dead",
            "OriginBlood": "",
            "Generation": "",
            "Speed": 11.14,
            "Jump": 0.0,
            "Health": 0.0,
            "Appearance": ""
        },
        "Shadow": {
            "Parent1": "Stripe II",
            "Parent2": "Speedy",
            "Status": "Alive",
            "OriginBlood": "",
            "Generation": "",
            "Speed": 12.11,
            "Jump": 2.68,
            "Health": 24.9,
            "Appearance": "Black w/ None"
        },
        "Brownscorch": {
            "Parent1": "Mirage II",
            "Parent2": "Cruiser II",
            "Status": "Alive",
            "OriginBlood": "",
            "Generation": "",
            "Speed": 12.57,
            "Jump": 4.23,
            "Health": 26.6,
            "Appearance": "Brown w/ Black Dots"
        },
        "Gray IV": {
            "Parent1": "Gray II",
            "Parent2": "Gray III",
            "Status": "Dead",
            "OriginBlood": "",
            "Generation": "",
            "Speed": 5.64,
            "Jump": 0.0,
            "Health": 0.0,
            "Appearance": "Gray w/ White Stockings/Blaze"
        },
        "Blondy IV": {
            "Parent1": "Blondy III",
            "Parent2": "Scorchback III",
            "Status": "Dead",
            "OriginBlood": "",
            "Generation": "",
            "Speed": 11.26,
            "Jump": 0.0,
            "Health": 0.0,
            "Appearance": ""
        },
        "Whitty X": {
            "Parent1": "Mirage",
            "Parent2": "Whitty II",
            "Status": "Dead",
            "OriginBlood": "",
            "Generation": "",
            "Speed": 10.97,
            "Jump": 0.0,
            "Health": 0.0,
            "Appearance": ""
        },
        "Light": {
            "Parent1": "Scorchback II",
            "Parent2": "Blondy",
            "Status": "Dead",
            "OriginBlood": "",
            "Generation": "",
            "Speed": 11.89,
            "Jump": 0.0,
            "Health": 0.0,
            "Appearance": ""
        },
        "Camspot V": {
            "Parent1": "Spooky",
            "Parent2": "Camspot IV",
            "Status": "Alive",
            "OriginBlood": "",
            "Generation": "",
            "Speed": 12.17,
            "Jump": 4.09,
            "Health": 24.8,
            "Appearance": "Creamy w/ White Dots"
        },
        "Cruiser IV": {
            "Parent1": "Cruiser",
            "Parent2": "Stripe II",
            "Status": "Dead",
            "OriginBlood": "",
            "Generation": "",
            "Speed": 11.69,
            "Jump": 0.0,
            "Health": 0.0,
            "Appearance": ""
        },
        "Speedy III": {
            "Parent1": "Speedy",
            "Parent2": "Shadow",
            "Status": "Alive",
            "OriginBlood": "",
            "Generation": "",
            "Speed": 11.98,
            "Jump": 3.9,
            "Health": 25.2,
            "Appearance": "Black w/ White Dots"
        },
        "White Socks II": {
            "Parent1": "Mirage II",
            "Parent2": "White Socks I",
            "Status": "Alive",
            "OriginBlood": "",
            "Generation": "",
            "Speed": 12.78,
            "Jump": 2.39,
            "Health": 26.1,
            "Appearance": "Chestnut w/ White Stockings/Blaze"
        },
        "Brownspot I": {
            "Parent1": "Brownscorch",
            "Parent2": "Cruiser II",
            "Status": "Alive",
            "OriginBlood": "",
            "Generation": "",
            "Speed": 12.5,
            "Jump": 4.03,
            "Health": 24.5,
            "Appearance": "Brown w/ White Dots"
        },
        "Gray V": {
            "Parent1": "Gray II",
            "Parent2": "Gray III",
            "Status": "Alive",
            "OriginBlood": "",
            "Generation": "",
            "Speed": 5.03,
            "Jump": 2.58,
            "Health": 21.1,
            "Appearance": "Gray w/ White Stockings/Blaze"
        },
        "Blondy V": {
            "Parent1": "Blondy",
            "Parent2": "Light",
            "Status": "Dead",
            "OriginBlood": "",
            "Generation": "",
            "Speed": 11.46,
            "Jump": 2.29,
            "Health": 27.0,
            "Appearance": "Chestnut w/ White Patches"
        },
        "Spooky II": {
            "Parent1": "Spooky",
            "Parent2": "Camspot IV",
            "Status": "Dead",
            "OriginBlood": "",
            "Generation": "",
            "Speed": 11.51,
            "Jump": 0.0,
            "Health": 0.0,
            "Appearance": "Black w/ White Patches"
        },
        "Spooky III": {
            "Parent1": "Cruiser",
            "Parent2": "Speedy III",
            "Status": "Alive",
            "OriginBlood": "",
            "Generation": "",
            "Speed": 12.51,
            "Jump": 3.84,
            "Health": 25.0,
            "Appearance": "Black w/ White Patches"
        },
        "Speedy IV": {
            "Parent1": "Stripe II",
            "Parent2": "Speedy",
            "Status": "Dead",
            "OriginBlood": "",
            "Generation": "",
            "Speed": 11.84,
            "Jump": 0.0,
            "Health": 0.0,
            "Appearance": ""
        },
        "Grayspot I": {
            "Parent1": "Shadow",
            "Parent2": "Camspot V",
            "Status": "Dead",
            "OriginBlood": "",
            "Generation": "",
            "Speed": 11.41,
            "Jump": 0.0,
            "Health": 0.0,
            "Appearance": ""
        },
        "Light II": {
            "Parent1": "Mirage II",
            "Parent2": "White Socks I",
            "Status": "Alive",
            "OriginBlood": "",
            "Generation": "",
            "Speed": 12.21,
            "Jump": 2.09,
            "Health": 27.7,
            "Appearance": "White w/ White Stockings/Blaze"
        },
        "Brownspot III": {
            "Parent1": "Brownspot I",
            "Parent2": "Brownscorch",
            "Status": "Alive",
            "OriginBlood": "",
            "Generation": "",
            "Speed": 12.14,
            "Jump": 3.87,
            "Health": 25.7,
            "Appearance": "Brown w/ White Dots"
        },
        "Scorchback IV": {
            "Parent1": "Cruiser II",
            "Parent2": "White Socks II",
            "Status": "Alive",
            "OriginBlood": "",
            "Generation": "",
            "Speed": 12.55,
            "Jump": 3.28,
            "Health": 27.8,
            "Appearance": "Chestnut w/ Black Dots"
        },
        "Gray VI": {
            "Parent1": "Gray IV",
            "Parent2": "Gray III",
            "Status": "Dead",
            "OriginBlood": "",
            "Generation": "",
            "Speed": 5.2,
            "Jump": 0.0,
            "Health": 0.0,
            "Appearance": "Gray w/ White Stockings/Blaze"
        }
    },
    "positions": {
        "Speedy": [
            -100.0,
            0.0
        ],
        "Blondy": [
            -80.0,
            0.0
        ],
        "Whitty I": [
            -60.0,
            0.0
        ],
        "Spotty": [
            -40.0,
            0.0
        ],
        "Camemille": [
            -20.0,
            0.0
        ],
        "White V": [
            0.0,
            0.0
        ],
        "Pure": [
            20.0,
            0.0
        ],
        "Scorchback": [
            40.0,
            0.0
        ],
        "Gray": [
            60.0,
            0.0
        ],
        "Snail": [
            80.0,
            0.0
        ],
        "Cruiser": [
            -110.0,
            -15.0
        ],
        "Whitty II": [
            -90.0,
            -15.0
        ],
        "White VIII": [
            -70.0,
            -15.0
        ],
        "Stripe": [
            -50.0,
            -15.0
        ],
        "Spotty II": [
            -30.0,
            -15.0
        ],
        "Blotty": [
            -10.0,
            -15.0
        ],
        "Pure Spots": [
            10.0,
            -15.0
        ],
        "White VI": [
            30.0,
            -15.0
        ],
        "White VII": [
            50.0,
            -15.0
        ],
        "White Face": [
            70.0,
            -15.0
        ],
        "Blackback": [
            90.0,
            -15.0
        ],
        "Cruiser II": [
            -120.0,
            -30.0
        ],
        "Spooky": [
            -100.0,
            -30.0
        ],
        "Scorchback II": [
            -80.0,
            -30.0
        ],
        "Camemille V": [
            -60.0,
            -30.0
        ],
        "Speedy II": [
            -40.0,
            -30.0
        ],
        "Camspot": [
            -20.0,
            -30.0
        ],
        "Spotty III": [
            0.0,
            -30.0
        ],
        "Pure II": [
            20.0,
            -30.0
        ],
        "Camemille IV": [
            40.0,
            -30.0
        ],
        "Camspot II": [
            60.0,
            -30.0
        ],
        "Camemille III": [
            80.0,
            -30.0
        ],
        "Gray II": [
            100.0,
            -30.0
        ],
        "White Socks I": [
            -120.0,
            -45.0
        ],
        "Mirage II": [
            -100.0,
            -45.0
        ],
        "Stripe II": [
            -80.0,
            -45.0
        ],
        "Camspot IV": [
            -60.0,
            -45.0
        ],
        "Light": [
            -40.0,
            -45.0
        ],
        "Scorchback III": [
            -20.0,
            -45.0
        ],
        "Blondy II": [
            0.0,
            -45.0
        ],
        "Camemille II": [
            20.0,
            -45.0
        ],
        "Cruiser III": [
            40.0,
            -45.0
        ],
        "White IX": [
            60.0,
            -45.0
        ],
        "Blackback II": [
            80.0,
            -45.0
        ],
        "Gray III": [
            100.0,
            -45.0
        ],
        "White Socks II": [
            -150.0,
            -60.0
        ],
        "Brownscorch": [
            -130.0,
            -60.0
        ],
        "Light II": [
            -110.0,
            -60.0
        ],
        "Camspot V": [
            -90.0,
            -60.0
        ],
        "Shadow": [
            -70.0,
            -60.0
        ],
        "Speedy IV": [
            -50.0,
            -60.0
        ],
        "Cruiser IV": [
            -30.0,
            -60.0
        ],
        "Mirage": [
            -10.0,
            -60.0
        ],
        "Blondy III": [
            10.0,
            -60.0
        ],
        "Spooky II": [
            30.0,
            -60.0
        ],
        "Blondy V": [
            50.0,
            -60.0
        ],
        "Camspot III": [
            70.0,
            -60.0
        ],
        "Camemille VI": [
            90.0,
            -60.0
        ],
        "Gray IV": [
            110.0,
            -60.0
        ],
        "Gray V": [
            130.0,
            -60.0
        ],
        "Scorchback IV": [
            -80.0,
            -75.0
        ],
        "Brownspot I": [
            -60.0,
            -75.0
        ],
        "Speedy III": [
            -40.0,
            -75.0
        ],
        "Grayspot I": [
            -20.0,
            -75.0
        ],
        "Mirage III": [
            0.0,
            -75.0
        ],
        "Blondy IV": [
            20.0,
            -75.0
        ],
        "Whitty X": [
            40.0,
            -75.0
        ],
        "Gray VI": [
            60.0,
            -75.0
        ],
        "Spooky III": [
            -20.0,
            -90.0
        ],
        "Brownspot III": [
            0.0,
            -90.0
        ]
    },
    "ancestors": {
        "Speedy": [
            "Speedy"
        ],
        "Blondy": [
            "Blondy"
        ],
        "Whitty I": [
            "Whitty I"
        ],
        "Spotty": [
            "Spotty"
        ],
        "Camemille": [
            "Camemille"
        ],
        "White V": [
            "White V"
        ],
        "Pure": [
            "Pure"
        ],
        "Scorchback": [
            "Scorchback"
        ],
        "Snail": [
            "Snail"
        ],
        "Gray": [
            "Gray"
        ],
        "Whitty II": [
            "Spotty",
            "Whitty I",
            "Whitty II"
        ],
        "Cruiser": [
            "Blondy",
            "Speedy",
            "Cruiser"
        ],
        "Stripe": [
            "Scorchback",
            "Pure",
            "Stripe"
        ],
        "Blackback": [
            "Blackback",
            "Gray",
            "Snail"
        ],
        "White Face": [
            "White V",
            "White Face",
            "Camemille"
        ],
        "Scorchback II": [
            "Spotty",
            "Blondy",
            "Whitty I",
            "Whitty II",
            "Scorchback II"
        ],
        "Speedy II": [
            "Blondy",
            "Speedy II",
            "Speedy",
            "Cruiser"
        ],
        "Camspot": [
            "Pure",
            "Scorchback",
            "Stripe",
            "Camspot",
            "Whitty I"
        ],
        "Spotty II": [
            "Spotty",
            "Spotty II",
            "Camemille"
        ],
        "Pure Spots": [
            "White V",
            "Pure Spots",
            "Pure"
        ],
        "White VI": [
            "White V",
            "Pure",
            "White VI"
        ],
        "Gray II": [
            "Blackback",
            "Gray",
            "Gray II",
            "Snail"
        ],
        "White VII": [
            "White V",
            "Pure",
            "White VII"
        ],
        "Camspot II": [
            "Spotty",
            "Spotty II",
            "Camspot II",
            "Camemille"
        ],
        "White VIII": [
            "Spotty",
            "Whitty I",
            "White VIII"
        ],
        "Camemille II": [
            "Pure",
            "Scorchback",
            "Camemille II",
            "Stripe",
            "Camspot",
            "Whitty I"
        ],
        "White IX": [
            "Speedy",
            "Whitty II",
            "White IX",
            "Spotty",
            "Blondy",
            "Cruiser",
            "Whitty I",
            "Speedy II"
        ],
        "Scorchback III": [
            "Scorchback III",
            "Spotty",
            "Blondy",
            "Whitty I",
            "Whitty II",
            "Scorchback II"
        ],
        "Spooky": [
            "Speedy",
            "Spooky",
            "Blondy",
            "Cruiser"
        ],
        "Blackback II": [
            "Blackback",
            "Blackback II",
            "Gray",
            "Gray II",
            "Snail"
        ],
        "Spotty III": [
            "Spotty III",
            "Spotty",
            "Spotty II",
            "Camemille"
        ],
        "Camemille III": [
            "Spotty",
            "Spotty II",
            "Camemille III",
            "Camemille"
        ],
        "Pure II": [
            "Spotty",
            "Pure II",
            "Spotty II",
            "Camemille"
        ],
        "Blotty": [
            "Spotty",
            "Whitty I",
            "Blotty"
        ],
        "Stripe II": [
            "Scorchback",
            "Pure",
            "Stripe",
            "Camspot",
            "Stripe II",
            "Whitty I"
        ],
        "Camspot III": [
            "Camspot III",
            "Speedy",
            "Pure",
            "Scorchback",
            "Camemille II",
            "Stripe",
            "Blondy",
            "Cruiser",
            "Camspot",
            "Whitty I",
            "Speedy II"
        ],
        "Mirage": [
            "Whitty II",
            "Scorchback III",
            "Spotty",
            "Blondy",
            "White VIII",
            "Whitty I",
            "Scorchback II",
            "Mirage"
        ],
        "Mirage II": [
            "Spotty",
            "Blondy",
            "Whitty I",
            "Whitty II",
            "Scorchback II",
            "Mirage II"
        ],
        "Blondy II": [
            "Speedy",
            "Blondy II",
            "Spooky",
            "Blondy",
            "Cruiser"
        ],
        "Cruiser II": [
            "Blondy",
            "Speedy",
            "Cruiser II",
            "Cruiser"
        ],
        "Gray III": [
            "Blackback",
            "Gray",
            "Gray II",
            "Snail",
            "Gray III"
        ],
        "Camemille IV": [
            "Spotty",
            "Camemille",
            "Spotty II",
            "Camemille IV"
        ],
        "Camemille V": [
            "Spotty",
            "Camemille V",
            "Spotty II",
            "Camemille"
        ],
        "Camemille VI": [
            "Speedy",
            "Camemille VI",
            "Pure",
            "Scorchback",
            "Camemille II",
            "Stripe",
            "Blondy",
            "Cruiser",
            "Camspot",
            "Whitty I",
            "Speedy II"
        ],
        "Camspot IV": [
            "Spotty II",
            "Camspot IV",
            "Camemille",
            "Spotty",
            "Camemille V",
            "White VIII",
            "Whitty I"
        ],
        "Blondy III": [
            "Blondy III",
            "Speedy",
            "Blondy II",
            "Whitty II",
            "Spooky",
            "Scorchback III",
            "Spotty",
            "Blondy",
            "Cruiser",
            "Whitty I",
            "Scorchback II"
        ],
        "Mirage III": [
            "Mirage",
            "Scorchback III",
            "Spotty",
            "Blondy",
            "White VIII",
            "Whitty II",
            "Whitty I",
            "Scorchback II",
            "Mirage III"
        ],
        "White Socks I": [
            "Spotty",
            "Blondy",
            "Whitty I",
            "Whitty II",
            "White Socks I",
            "Scorchback II"
        ],
        "Cruiser III": [
            "Cruiser III",
            "Speedy",
            "Spooky",
            "Blondy",
            "Cruiser"
        ],
        "Shadow": [
            "Speedy",
            "Pure",
            "Scorchback",
            "Stripe",
            "Camspot",
            "Stripe II",
            "Shadow",
            "Whitty I"
        ],
        "Brownscorch": [
            "Speedy",
            "Cruiser II",
            "Brownscorch",
            "Spotty",
            "Blondy",
            "Whitty I",
            "Whitty II",
            "Cruiser",
            "Scorchback II",
            "Mirage II"
        ],
        "Gray IV": [
            "Blackback",
            "Gray",
            "Gray II",
            "Snail",
            "Gray IV",
            "Gray III"
        ],
        "Blondy IV": [
            "Blondy III",
            "Speedy",
            "Blondy II",
            "Spooky",
            "Scorchback III",
            "Blondy IV",
            "Spotty",
            "Blondy",
            "Cruiser",
            "Whitty II",
            "Whitty I",
            "Scorchback II"
        ],
        "Whitty X": [
            "Scorchback III",
            "Spotty",
            "Blondy",
            "White VIII",
            "Whitty II",
            "Whitty I",
            "Scorchback II",
            "Mirage",
            "Whitty X"
        ],
        "Light": [
            "Light",
            "Spotty",
            "Blondy",
            "Whitty I",
            "Whitty II",
            "Scorchback II"
        ],
        "Camspot V": [
            "Speedy",
            "Spooky",
            "Spotty II",
            "Camspot IV",
            "Camemille",
            "Spotty",
            "Camemille V",
            "Blondy",
            "Cruiser",
            "White VIII",
            "Whitty I",
            "Camspot V"
        ],
        "Cruiser IV": [
            "Cruiser IV",
            "Speedy",
            "Scorchback",
            "Pure",
            "Stripe",
            "Blondy",
            "Cruiser",
            "Camspot",
            "Stripe II",
            "Whitty I"
        ],
        "Speedy III": [
            "Speedy",
            "Scorchback",
            "Pure",
            "Speedy III",
            "Stripe",
            "Camspot",
            "Stripe II",
            "Shadow",
            "Whitty I"
        ],
        "White Socks II": [
            "White Socks II",
            "Spotty",
            "Blondy",
            "Whitty I",
            "Whitty II",
            "White Socks I",
            "Scorchback II",
            "Mirage II"
        ],
        "Brownspot I": [
            "Cruiser II",
            "Speedy",
            "Brownspot I",
            "Brownscorch",
            "Spotty",
            "Blondy",
            "Whitty I",
            "Whitty II",
            "Cruiser",
            "Scorchback II",
            "Mirage II"
        ],
        "Gray V": [
            "Blackback",
            "Gray",
            "Gray II",
            "Snail",
            "Gray V",
            "Gray III"
        ],
        "Blondy V": [
            "Blondy V",
            "Light",
            "Spotty",
            "Blondy",
            "Whitty I",
            "Whitty II",
            "Scorchback II"
        ],
        "Spooky II": [
            "Speedy",
            "Spooky II",
            "Spooky",
            "Spotty II",
            "Camspot IV",
            "Camemille",
            "Spotty",
            "Camemille V",
            "Blondy",
            "Cruiser",
            "White VIII",
            "Whitty I"
        ],
        "Spooky III": [
            "Speedy",
            "Scorchback",
            "Pure",
            "Speedy III",
            "Stripe",
            "Blondy",
            "Cruiser",
            "Camspot",
            "Spooky III",
            "Stripe II",
            "Whitty I",
            "Shadow"
        ],
        "Speedy IV": [
            "Speedy",
            "Pure",
            "Scorchback",
            "Speedy IV",
            "Stripe",
            "Camspot",
            "Stripe II",
            "Whitty I"
        ],
        "Grayspot I": [
            "Camemille",
            "Whitty I",
            "Speedy",
            "Scorchback",
            "Pure",
            "Spooky",
            "Camspot IV",
            "Spotty",
            "White VIII",
            "Shadow",
            "Grayspot I",
            "Camspot V",
            "Spotty II",
            "Stripe",
            "Camemille V",
            "Camspot",
            "Stripe II",
            "Blondy",
            "Cruiser"
        ],
        "Light II": [
            "Light II",
            "Spotty",
            "Blondy",
            "Whitty I",
            "Whitty II",
            "White Socks I",
            "Scorchback II",
            "Mirage II"
        ],
        "Brownspot III": [
            "Speedy",
            "Cruiser II",
            "Brownspot III",
            "Brownspot I",
            "Brownscorch",
            "Spotty",
            "Blondy",
            "Whitty I",
            "Whitty II",
            "Cruiser",
            "Scorchback II",
            "Mirage II"
        ],
        "Scorchback IV": [
            "Scorchback IV",
            "Cruiser II",
            "Speedy",
            "Whitty II",
            "White Socks II",
            "Spotty",
            "Blondy",
            "Cruiser",
            "Whitty I",
            "White Socks I",
            "Scorchback II",
            "Mirage II"
        ],
        "Gray VI": [
            "Blackback",
            "Gray VI",
            "Gray",
            "Gray II",
            "Snail",
            "Gray IV",
            "Gray III"
        ]
    },
    "descendants": {
        "Speedy": [
            "Cruiser IV",
            "Blondy III",
            "Cruiser III",
            "Camspot III",
            "Blondy II",
            "Brownscorch",
            "Camemille VI",
            "Spooky II",
            "Speedy III",
            "Spooky",
            "Shadow",
            "Camspot V",
            "Grayspot I",
            "Cruiser II",
            "Speedy IV",
            "Brownspot III",
            "White IX",
            "Scorchback IV",
            "Blondy IV",
            "Brownspot I",
            "Cruiser",
            "Spooky III",
            "Speedy II",
            "Speedy"
        ],
        "Blondy": [
            "Cruiser IV",
            "Blondy III",
            "Cruiser III",
            "Camspot III",
            "Blondy II",
            "White Socks II",
            "Brownscorch",
            "Mirage II",
            "Blondy V",
            "Camemille VI",
            "Spooky II",
            "Spooky",
            "White Socks I",
            "Grayspot I",
            "Camspot V",
            "Cruiser II",
            "Brownspot III",
            "Light",
            "Scorchback III",
            "White IX",
            "Mirage III",
            "Whitty X",
            "Light II",
            "Scorchback IV",
            "Blondy IV",
            "Brownspot I",
            "Cruiser",
            "Spooky III",
            "Scorchback II",
            "Speedy II",
            "Mirage",
            "Blondy"
        ],
        "Whitty I": [
            "Blondy III",
            "Cruiser IV",
            "Camspot III",
            "White Socks II",
            "Brownscorch",
            "Mirage II",
            "Blondy V",
            "Camemille VI",
            "Spooky II",
            "Speedy III",
            "Camspot IV",
            "Blotty",
            "Whitty II",
            "White VIII",
            "White Socks I",
            "Shadow",
            "Grayspot I",
            "Camspot V",
            "Speedy IV",
            "Brownspot III",
            "Light",
            "Scorchback III",
            "White IX",
            "Camspot",
            "Stripe II",
            "Mirage III",
            "Whitty X",
            "Light II",
            "Scorchback IV",
            "Camemille II",
            "Blondy IV",
            "Brownspot I",
            "Spooky III",
            "Scorchback II",
            "Mirage",
            "Whitty I"
        ],
        "Spotty": [
            "Blondy III",
            "Pure II",
            "White Socks II",
            "Brownscorch",
            "Camspot II",
            "Mirage II",
            "Blondy V",
            "Camemille III",
            "Spooky II",
            "Camspot IV",
            "Blotty",
            "Whitty II",
            "White VIII",
            "White Socks I",
            "Camemille IV",
            "Camspot V",
            "Grayspot I",
            "Brownspot III",
            "Spotty II",
            "Light",
            "Scorchback III",
            "White IX",
            "Camemille V",
            "Mirage III",
            "Whitty X",
            "Spotty III",
            "Light II",
            "Scorchback IV",
            "Blondy IV",
            "Brownspot I",
            "Scorchback II",
            "Mirage",
            "Spotty"
        ],
        "Camemille": [
            "Spotty III",
            "Pure II",
            "White Face",
            "Camemille III",
            "Spooky II",
            "Spotty II",
            "Camspot IV",
            "Camemille V",
            "Camspot II",
            "Camemille IV",
            "Grayspot I",
            "Camspot V",
            "Camemille"
        ],
        "White V": [
            "White VII",
            "White Face",
            "Pure Spots",
            "White VI",
            "White V"
        ],
        "Pure": [
            "Cruiser IV",
            "Camspot III",
            "Camemille VI",
            "Camemille II",
            "Speedy IV",
            "Speedy III",
            "Stripe",
            "Pure Spots",
            "Camspot",
            "White VII",
            "Stripe II",
            "Shadow",
            "Grayspot I",
            "Spooky III",
            "White VI",
            "Pure"
        ],
        "Scorchback": [
            "Cruiser IV",
            "Camspot III",
            "Camemille VI",
            "Camemille II",
            "Speedy IV",
            "Speedy III",
            "Stripe",
            "Camspot",
            "Stripe II",
            "Shadow",
            "Spooky III",
            "Grayspot I",
            "Scorchback"
        ],
        "Snail": [
            "Blackback",
            "Blackback II",
            "Gray VI",
            "Gray II",
            "Gray IV",
            "Gray V",
            "Gray III",
            "Snail"
        ],
        "Gray": [
            "Blackback",
            "Blackback II",
            "Gray VI",
            "Gray II",
            "Gray IV",
            "Gray V",
            "Gray III",
            "Gray"
        ],
        "Whitty II": [
            "Blondy III",
            "Light II",
            "Scorchback IV",
            "Mirage II",
            "Blondy V",
            "White Socks II",
            "Brownspot III",
            "Light",
            "Scorchback III",
            "Blondy IV",
            "White IX",
            "Brownscorch",
            "Brownspot I",
            "Mirage",
            "White Socks I",
            "Scorchback II",
            "Mirage III",
            "Whitty X",
            "Whitty II"
        ],
        "Cruiser": [
            "Cruiser IV",
            "Blondy III",
            "Cruiser III",
            "Camspot III",
            "Blondy II",
            "Brownscorch",
            "Camemille VI",
            "Spooky II",
            "Spooky",
            "Camspot V",
            "Grayspot I",
            "Cruiser II",
            "Brownspot III",
            "White IX",
            "Scorchback IV",
            "Blondy IV",
            "Brownspot I",
            "Spooky III",
            "Speedy II",
            "Cruiser"
        ],
        "Stripe": [
            "Cruiser IV",
            "Camspot III",
            "Camemille VI",
            "Camemille II",
            "Speedy IV",
            "Speedy III",
            "Camspot",
            "Stripe II",
            "Shadow",
            "Spooky III",
            "Grayspot I",
            "Stripe"
        ],
        "Blackback": [
            "Blackback II",
            "Gray VI",
            "Gray II",
            "Gray IV",
            "Gray V",
            "Gray III",
            "Blackback"
        ],
        "White Face": [
            "White Face"
        ],
        "Scorchback II": [
            "Blondy III",
            "Light II",
            "Scorchback IV",
            "Blondy V",
            "White Socks II",
            "Mirage III",
            "Brownspot III",
            "Light",
            "Scorchback III",
            "Blondy IV",
            "Whitty X",
            "Brownscorch",
            "Brownspot I",
            "White Socks I",
            "Mirage",
            "Mirage II",
            "Scorchback II"
        ],
        "Speedy II": [
            "White IX",
            "Camspot III",
            "Camemille VI",
            "Speedy II"
        ],
        "Camspot": [
            "Cruiser IV",
            "Camspot III",
            "Camemille VI",
            "Camemille II",
            "Speedy IV",
            "Speedy III",
            "Stripe II",
            "Shadow",
            "Spooky III",
            "Grayspot I",
            "Camspot"
        ],
        "Spotty II": [
            "Spotty III",
            "Pure II",
            "Camemille III",
            "Spooky II",
            "Camspot IV",
            "Camemille V",
            "Camspot II",
            "Camspot V",
            "Camemille IV",
            "Grayspot I",
            "Spotty II"
        ],
        "Pure Spots": [
            "Pure Spots"
        ],
        "White VI": [
            "White VI"
        ],
        "Gray II": [
            "Blackback II",
            "Gray VI",
            "Gray IV",
            "Gray V",
            "Gray III",
            "Gray II"
        ],
        "White VII": [
            "White VII"
        ],
        "Camspot II": [
            "Camspot II"
        ],
        "White VIII": [
            "Spooky II",
            "Mirage",
            "Camspot IV",
            "Camspot V",
            "Grayspot I",
            "Mirage III",
            "Whitty X",
            "White VIII"
        ],
        "Camemille II": [
            "Camspot III",
            "Camemille VI",
            "Camemille II"
        ],
        "White IX": [
            "White IX"
        ],
        "Scorchback III": [
            "Blondy III",
            "Mirage",
            "Blondy IV",
            "Mirage III",
            "Whitty X",
            "Scorchback III"
        ],
        "Spooky": [
            "Blondy III",
            "Cruiser III",
            "Blondy II",
            "Spooky II",
            "Blondy IV",
            "Grayspot I",
            "Camspot V",
            "Spooky"
        ],
        "Blackback II": [
            "Blackback II"
        ],
        "Spotty III": [
            "Spotty III"
        ],
        "Camemille III": [
            "Camemille III"
        ],
        "Pure II": [
            "Pure II"
        ],
        "Blotty": [
            "Blotty"
        ],
        "Stripe II": [
            "Cruiser IV",
            "Speedy IV",
            "Speedy III",
            "Shadow",
            "Spooky III",
            "Grayspot I",
            "Stripe II"
        ],
        "Camspot III": [
            "Camspot III"
        ],
        "Mirage": [
            "Mirage III",
            "Whitty X",
            "Mirage"
        ],
        "Mirage II": [
            "Light II",
            "Scorchback IV",
            "White Socks II",
            "Brownspot III",
            "Brownscorch",
            "Brownspot I",
            "Mirage II"
        ],
        "Blondy II": [
            "Blondy III",
            "Blondy IV",
            "Blondy II"
        ],
        "Cruiser II": [
            "Brownscorch",
            "Brownspot I",
            "Scorchback IV",
            "Brownspot III",
            "Cruiser II"
        ],
        "Gray III": [
            "Gray IV",
            "Gray VI",
            "Gray V",
            "Gray III"
        ],
        "Camemille IV": [
            "Camemille IV"
        ],
        "Camemille V": [
            "Spooky II",
            "Grayspot I",
            "Camspot V",
            "Camspot IV",
            "Camemille V"
        ],
        "Camemille VI": [
            "Camemille VI"
        ],
        "Camspot IV": [
            "Spooky II",
            "Grayspot I",
            "Camspot V",
            "Camspot IV"
        ],
        "Blondy III": [
            "Blondy IV",
            "Blondy III"
        ],
        "Mirage III": [
            "Mirage III"
        ],
        "White Socks I": [
            "White Socks II",
            "Scorchback IV",
            "Light II",
            "White Socks I"
        ],
        "Cruiser III": [
            "Cruiser III"
        ],
        "Shadow": [
            "Spooky III",
            "Speedy III",
            "Grayspot I",
            "Shadow"
        ],
        "Brownscorch": [
            "Brownspot I",
            "Brownspot III",
            "Brownscorch"
        ],
        "Gray IV": [
            "Gray VI",
            "Gray IV"
        ],
        "Blondy IV": [
            "Blondy IV"
        ],
        "Whitty X": [
            "Whitty X"
        ],
        "Light": [
            "Blondy V",
            "Light"
        ],
        "Camspot V": [
            "Grayspot I",
            "Camspot V"
        ],
        "Cruiser IV": [
            "Cruiser IV"
        ],
        "Speedy III": [
            "Spooky III",
            "Speedy III"
        ],
        "White Socks II": [
            "Scorchback IV",
            "White Socks II"
        ],
        "Brownspot I": [
            "Brownspot III",
            "Brownspot I"
        ],
        "Gray V": [
            "Gray V"
        ],
        "Blondy V": [
            "Blondy V"
        ],
        "Spooky II": [
            "Spooky II"
        ],
        "Spooky III": [
            "Spooky III"
        ],
        "Speedy IV": [
            "Speedy IV"
        ],
        "Grayspot I": [
            "Grayspot I"
        ],
        "Light II": [
            "Light II"
        ],
        "Brownspot III": [
            "Brownspot III"
        ],
        "Scorchback IV": [
            "Scorchback IV"
        ],
        "Gray VI": [
            "Gray VI"
        ]
    },
    "origin_colors": {
        "Star Strider": "#FFD700",
        "Celestial Grass": "#00FF7F",
        "Thunder Blood": "#FF004F",
        "Frostmane": "#00D4FF",
        "Emberhoof": "#FF8C00",
        "Slothsoul": "#708090",
        "Unknown": "#444444"
    },
    "stats": {
        "top_16_speed": [
            {
                "Name": "White Socks II",
                "Speed": 12.78
            },
            {
                "Name": "Cruiser II",
                "Speed": 12.58
            },
            {
                "Name": "Brownscorch",
                "Speed": 12.57
            },
            {
                "Name": "Scorchback IV",
                "Speed": 12.55
            },
            {
                "Name": "Spooky III",
                "Speed": 12.51
            },
            {
                "Name": "Brownspot I",
                "Speed": 12.5
            },
            {
                "Name": "White Socks I",
                "Speed": 12.33
            },
            {
                "Name": "Light II",
                "Speed": 12.21
            },
            {
                "Name": "Mirage II",
                "Speed": 12.17
            },
            {
                "Name": "Camspot V",
                "Speed": 12.17
            },
            {
                "Name": "Brownspot III",
                "Speed": 12.14
            },
            {
                "Name": "Shadow",
                "Speed": 12.11
            },
            {
                "Name": "Speedy",
                "Speed": 12.06
            },
            {
                "Name": "Stripe II",
                "Speed": 11.99
            },
            {
                "Name": "Speedy III",
                "Speed": 11.98
            },
            {
                "Name": "Cruiser",
                "Speed": 11.95
            }
        ],
        "top_16_jump": [
            {
                "Name": "Cruiser II",
                "Jump": 4.87
            },
            {
                "Name": "Speedy",
                "Jump": 4.75
            },
            {
                "Name": "Brownscorch",
                "Jump": 4.23
            },
            {
                "Name": "Camspot V",
                "Jump": 4.09
            },
            {
                "Name": "Brownspot I",
                "Jump": 4.03
            },
            {
                "Name": "Speedy III",
                "Jump": 3.9
            },
            {
                "Name": "Brownspot III",
                "Jump": 3.87
            },
            {
                "Name": "Spooky III",
                "Jump": 3.84
            },
            {
                "Name": "Cruiser",
                "Jump": 3.68
            },
            {
                "Name": "Scorchback IV",
                "Jump": 3.28
            },
            {
                "Name": "Mirage II",
                "Jump": 3.23
            },
            {
                "Name": "Gray III",
                "Jump": 2.69
            },
            {
                "Name": "Shadow",
                "Jump": 2.68
            },
            {
                "Name": "Gray V",
                "Jump": 2.58
            },
            {
                "Name": "White Socks II",
                "Jump": 2.39
            },
            {
                "Name": "Stripe II",
                "Jump": 2.18
            }
        ],
        "top_16_health": [
            {
                "Name": "Mirage II",
                "Health": 28.0
            },
            {
                "Name": "Scorchback IV",
                "Health": 27.8
            },
            {
                "Name": "Light II",
                "Health": 27.7
            },
            {
                "Name": "White Socks I",
                "Health": 27.0
            },
            {
                "Name": "Brownscorch",
                "Health": 26.6
            },
            {
                "Name": "White Socks II",
                "Health": 26.1
            },
            {
                "Name": "Brownspot III",
                "Health": 25.7
            },
            {
                "Name": "Stripe II",
                "Health": 25.2
            },
            {
                "Name": "Speedy III",
                "Health": 25.2
            },
            {
                "Name": "Spooky III",
                "Health": 25.0
            },
            {
                "Name": "Shadow",
                "Health": 24.9
            },
            {
                "Name": "Camspot V",
                "Health": 24.8
            },
            {
                "Name": "Cruiser",
                "Health": 24.7
            },
            {
                "Name": "Brownspot I",
                "Health": 24.5
            },
            {
                "Name": "Speedy",
                "Health": 24.0
            },
            {
                "Name": "Cruiser II",
                "Health": 23.8
            }
        ],
        "avg_speed": {
            "0": 11.0,
            "1": 10.33,
            "2": 10.67,
            "3": 10.58,
            "4": 10.95,
            "5": 10.9,
            "6": 12.32
        },
        "blood_all": {
            "Star Strider": 19.3,
            "Celestial Grass": 20.6,
            "Thunder Blood": 28.6,
            "Frostmane": 17.0,
            "Emberhoof": 14.5
        },
        "blood_alive": {
            "Star Strider": 39.3,
            "Celestial Grass": 26.6,
            "Thunder Blood": 24.2,
            "Emberhoof": 8.8,
            "Frostmane": 1.2
        }
    },
    "top3": {
        "speed": [
            "White Socks II",
            "Cruiser II",
            "Brownscorch"
        ],
        "jump": [
            "Cruiser II",
            "Speedy",
            "Brownscorch"
        ],
        "health": [
            "Mirage II",
            "Scorchback IV",
            "Light II"
        ]
    },
    "base_colors": {
        "Speedy": "#FFD700",
        "Blondy": "#00FF7F",
        "Whitty I": "#FF004F",
        "Spotty": "#FF004F",
        "Camemille": "#00D4FF",
        "White V": "#00D4FF",
        "Pure": "#FF8C00",
        "Scorchback": "#FF8C00",
        "Snail": "#708090",
        "Gray": "#708090",
        "Whitty II": "rgb(255,0,79)",
        "Cruiser": "rgb(127,235,63)",
        "Stripe": "rgb(255,140,0)",
        "Blackback": "rgb(112,128,144)",
        "White Face": "rgb(0,212,255)",
        "Scorchback II": "rgb(127,127,103)",
        "Speedy II": "rgb(191,225,31)",
        "Camspot": "rgb(255,70,39)",
        "Spotty II": "rgb(127,106,167)",
        "Pure Spots": "rgb(127,176,127)",
        "White VI": "rgb(127,176,127)",
        "Gray II": "rgb(112,128,144)",
        "White VII": "rgb(127,176,127)",
        "Camspot II": "rgb(63,159,211)",
        "White VIII": "rgb(255,0,79)",
        "Camemille II": "rgb(255,105,19)",
        "White IX": "rgb(223,112,55)",
        "Scorchback III": "rgb(63,191,115)",
        "Spooky": "rgb(191,225,31)",
        "Blackback II": "rgb(112,128,144)",
        "Spotty III": "rgb(63,159,211)",
        "Camemille III": "rgb(63,159,211)",
        "Pure II": "rgb(63,159,211)",
        "Blotty": "rgb(255,0,79)",
        "Stripe II": "rgb(255,105,19)",
        "Camspot III": "rgb(223,165,25)",
        "Mirage": "rgb(159,95,97)",
        "Mirage II": "rgb(191,63,91)",
        "Blondy II": "rgb(95,240,79)",
        "Cruiser II": "rgb(191,225,31)",
        "Gray III": "rgb(112,128,144)",
        "Camemille IV": "rgb(63,159,211)",
        "Camemille V": "rgb(63,159,211)",
        "Camemille VI": "rgb(223,165,25)",
        "Camspot IV": "rgb(159,79,145)",
        "Blondy III": "rgb(79,215,97)",
        "Mirage III": "rgb(207,47,88)",
        "White Socks I": "rgb(63,191,115)",
        "Cruiser III": "rgb(159,230,47)",
        "Shadow": "rgb(255,160,9)",
        "Brownscorch": "rgb(191,144,61)",
        "Gray IV": "rgb(112,128,144)",
        "Blondy IV": "rgb(71,203,106)",
        "Whitty X": "rgb(207,47,88)",
        "Light": "rgb(63,191,115)",
        "Camspot V": "rgb(175,152,88)",
        "Cruiser IV": "rgb(191,170,41)",
        "Speedy III": "rgb(255,187,4)",
        "White Socks II": "rgb(127,127,103)",
        "Brownspot I": "rgb(191,184,46)",
        "Gray V": "rgb(112,128,144)",
        "Blondy V": "rgb(31,223,121)",
        "Spooky II": "rgb(175,152,88)",
        "Spooky III": "rgb(191,211,34)",
        "Speedy IV": "rgb(255,160,9)",
        "Grayspot I": "rgb(215,156,49)",
        "Light II": "rgb(127,127,103)",
        "Brownspot III": "rgb(191,164,53)",
        "Scorchback IV": "rgb(159,176,67)",
        "Gray VI": "rgb(112,128,144)"
    }
}